VERSION
ahnlich_client_py/__init__.py
ahnlich_client_py/config.py
ahnlich_client_py/exceptions.py
ahnlich_client_py/grpc/__init__.py
ahnlich_client_py/grpc/ai/__init__.py
ahnlich_client_py/grpc/ai/execution_provider/__init__.py
ahnlich_client_py/grpc/ai/models/__init__.py
ahnlich_client_py/grpc/ai/pipeline/__init__.py
ahnlich_client_py/grpc/ai/preprocess/__init__.py
ahnlich_client_py/grpc/ai/query/__init__.py
ahnlich_client_py/grpc/ai/server/__init__.py
ahnlich_client_py/grpc/algorithm/__init__.py
ahnlich_client_py/grpc/algorithm/algorithms/__init__.py
ahnlich_client_py/grpc/algorithm/nonlinear/__init__.py
ahnlich_client_py/grpc/client/__init__.py
ahnlich_client_py/grpc/db/__init__.py
ahnlich_client_py/grpc/db/pipeline/__init__.py
ahnlich_client_py/grpc/db/query/__init__.py
ahnlich_client_py/grpc/db/server/__init__.py
ahnlich_client_py/grpc/keyval/__init__.py
ahnlich_client_py/grpc/metadata/__init__.py
ahnlich_client_py/grpc/predicates/__init__.py
ahnlich_client_py/grpc/server_types/__init__.py
ahnlich_client_py/grpc/services/__init__.py
ahnlich_client_py/grpc/services/ai_service/__init__.py
ahnlich_client_py/grpc/services/db_service/__init__.py
ahnlich_client_py/grpc/shared/__init__.py
ahnlich_client_py/grpc/shared/info/__init__.py
ahnlich_client_py/grpc/similarity/__init__.py
ahnlich_client_py/grpc/version/__init__.py
ahnlich_client_py-0.1.0.dist-info/METADATA
ahnlich_client_py-0.1.0.dist-info/WHEEL
ahnlich_client_py-0.1.0.dist-info/entry_points.txt
ahnlich_client_py-0.1.0.dist-info/RECORD
