Metadata-Version: 2.1
Name: ahnlich-client-py
Version: 0.1.0
Summary: A python client for interacting with Ahnlich DB and AI
Author: David Onuh
Author-email: davidonuh1@gmail.com
Requires-Python: >=3.11,<4.0
Classifier: Programming Language :: Python :: 3
Classifier: Programming Language :: Python :: 3.11
Classifier: Programming Language :: Python :: 3.12
Requires-Dist: betterproto[compiler] (>=2.0.0b7,<3.0.0)
Requires-Dist: bump2version (>=1.0.1,<2.0.0)
Requires-Dist: grpclib (>=0.4.1,<0.5.0)
Requires-Dist: pytest-asyncio (>=0.24.0,<0.25.0)
Requires-Dist: toml (>=0.10.2,<0.11.0)
